setup.py
spider_task_ip/__init__.py
spider_task_ip/config.py
spider_task_ip/init_config.py
spider_task_ip/ip_service.py
spider_task_ip/ip_vps_service.py
spider_task_ip_zy.egg-info/PKG-INFO
spider_task_ip_zy.egg-info/SOURCES.txt
spider_task_ip_zy.egg-info/dependency_links.txt
spider_task_ip_zy.egg-info/top_level.txt