Metadata-Version: 1.0
Name: spider-task-ip-zy
Version: 1.0.8
Summary: spider IP service
Home-page: UNKNOWN
Author: rain
Author-email: rainsee@zhiyitech.cn
License: UNKNOWN
Keywords: spider,ip
Platform: UNKNOWN
